ws_auth/__init__.py
ws_auth/__version__.py
ws_auth/auth.py
ws_auth/http.py
ws_auth/protocol.py
ws_auth/py.typed
ws_auth/types.py
ws_auth-0.1.0.dist-info/LICENSE.md
ws_auth-0.1.0.dist-info/METADATA
ws_auth-0.1.0.dist-info/WHEEL
ws_auth-0.1.0.dist-info/top_level.txt
ws_auth-0.1.0.dist-info/RECORD
